{
  "type": "FeatureCollection",
  "features": [
    {
      "type": "Feature",
      "properties": {
        "kind": "county",
        "name": "Tioga",
        "state": "NY",
        "filename": "C:\\Users\\pmend\\source\\repos\\world.geo.json\\combiner\\bin\\Debug\\netcoreapp2.0\\NY\\Tioga.geo.json",
        "originalid": null
      },
      "geometry": {
        "type": "Polygon",
        "coordinates": [
          [
            [
              -76.1316,
              42.4115
            ],
            [
              -76.2521,
              42.406
            ],
            [
              -76.3014,
              42.3841
            ],
            [
              -76.2411,
              42.3622
            ],
            [
              -76.2521,
              42.2965
            ],
            [
              -76.4164,
              42.3184
            ],
            [
              -76.4164,
              42.2636
            ],
            [
              -76.5369,
              42.28
            ],
            [
              -76.5588,
              42.0007
            ],
            [
              -76.148,
              42.0007
            ],
            [
              -76.1042,
              42.0007
            ],
            [
              -76.1151,
              42.1869
            ],
            [
              -76.0878,
              42.1869
            ],
            [
              -76.0823,
              42.2581
            ],
            [
              -76.1316,
              42.4115
            ]
          ]
        ]
      },
      "id": "54"
    }
  ]
}